tezzchain/__init__.py
tezzchain/app.py
tezzchain/constants.py
tezzchain/utils.py
tezzchain/chunker/__init__.py
tezzchain/chunker/text.py
tezzchain/configurations/__init__.py
tezzchain/configurations/global_configuration.py
tezzchain/configurations/prepare_configuration.py
tezzchain/configurations/chunkers/__init__.py
tezzchain/configurations/chunkers/basic.py
tezzchain/configurations/embedding_providers/__init__.py
tezzchain/configurations/embedding_providers/ollamaEmbedding.py
tezzchain/configurations/llm_providers/__init__.py
tezzchain/configurations/llm_providers/ollamaLLM.py
tezzchain/configurations/vectordb_providers/__init__.py
tezzchain/configurations/vectordb_providers/chroma.py
tezzchain/core/__init__.py
tezzchain/core/database.py
tezzchain/core/history.py
tezzchain/embedding/__init__.py
tezzchain/embedding/base.py
tezzchain/embedding/ollamaEmbedding.py
tezzchain/exceptions/__init__.py
tezzchain/llm/__init__.py
tezzchain/llm/base.py
tezzchain/llm/ollamaLLM.py
tezzchain/telemetry/__init__.py
tezzchain/telemetry/events.py
tezzchain/utilities/__init__.py
tezzchain/utilities/hashing.py
tezzchain/utilities/read_file.py
tezzchain/vectordb/__init__.py
tezzchain/vectordb/base.py
tezzchain/vectordb/chroma_vectordb.py
TezzChain-0.1.1.dist-info/METADATA
TezzChain-0.1.1.dist-info/WHEEL
TezzChain-0.1.1.dist-info/top_level.txt
TezzChain-0.1.1.dist-info/RECORD
